Metadata-Version: 2.4
Name: telegram-rag-bot
Version: 0.11.2
Summary: Production-ready Telegram FAQ bot with Russian LLMs, RAG, and multi-provider fallback
Author-email: Mikhail Malorod <secretbox3@gmail.com>
License: MIT
Project-URL: Homepage, https://github.com/MikhailMalorod/telegram-bot-universal
Project-URL: Documentation, https://github.com/MikhailMalorod/telegram-bot-universal#readme
Project-URL: Repository, https://github.com/MikhailMalorod/telegram-bot-universal
Project-URL: Bug Tracker, https://github.com/MikhailMalorod/telegram-bot-universal/issues
Keywords: telegram,bot,chatbot,rag,langchain,llm,gigachat,yandexgpt,faiss,opensearch
Classifier: Development Status :: 4 - Beta
Classifier: Intended Audience :: Developers
Classifier: Topic :: Communications :: Chat
Classifier: Topic :: Scientific/Engineering :: Artificial Intelligence
Classifier: License :: OSI Approved :: MIT License
Classifier: Programming Language :: Python :: 3
Classifier: Programming Language :: Python :: 3.11
Classifier: Programming Language :: Python :: 3.12
Classifier: Operating System :: OS Independent
Requires-Python: >=3.11
License-File: LICENSE
Requires-Dist: multi-llm-orchestrator[langchain,retrieval]<1.0.0,>=0.9.0
Requires-Dist: langchain>=1.0
Requires-Dist: langchain-classic<2.0,>=1.0
Requires-Dist: langchain-core>=0.1.0
Requires-Dist: langchain-community>=0.0.1
Requires-Dist: langchain-text-splitters>=0.0.1
Requires-Dist: python-telegram-bot<22.0,>=21.0
Requires-Dist: faiss-cpu>=1.7.0
Requires-Dist: pyyaml>=6.0
Requires-Dist: pydantic>=2.0
Requires-Dist: redis>=5.0
Requires-Dist: httpx>=0.24.0
Requires-Dist: opensearch-py>=2.3.0
Requires-Dist: aiohttp>=3.9.0
Requires-Dist: python-json-logger>=2.0.0
Requires-Dist: prometheus-client<0.20.0,>=0.19.0
Provides-Extra: dev
Requires-Dist: pytest>=7.4.0; extra == "dev"
Requires-Dist: pytest-asyncio>=0.21.0; extra == "dev"
Requires-Dist: pytest-cov>=4.1.0; extra == "dev"
Requires-Dist: black>=23.0.0; extra == "dev"
Requires-Dist: ruff>=0.1.0; extra == "dev"
Requires-Dist: mypy>=1.5.0; extra == "dev"
Provides-Extra: local
Requires-Dist: sentence-transformers>=2.2.0; extra == "local"
Dynamic: license-file
